nauscopia/__init__.py
nauscopia/model.py
nauscopia/setting.py
nauscopia/api/__init__.py
nauscopia/api/cli.py
nauscopia/cmd/__init__.py
nauscopia/cmd/install.py
nauscopia/horizon/__init__.py
nauscopia/horizon/algorithm.py
nauscopia/horizon/detector.py
nauscopia/horizon/stabilizer.py
nauscopia/roi/__init__.py
nauscopia/roi/detect/__init__.py
nauscopia/roi/detect/cli.py
nauscopia/roi/detect/opencv.py
nauscopia/roi/detect/opencv_boat_finder.py
nauscopia/roi/detect/opencv_candidates.py
nauscopia/roi/detect/yolo.py
nauscopia/roi/track/__init__.py
nauscopia/roi/track/stonesoup.py
nauscopia/util/__init__.py
nauscopia/util/cli.py
nauscopia/util/data.py
nauscopia/util/io.py
nauscopia/util/log.py
tests/__init__.py
tests/conftest.py
tests/test_cli.py
tests/test_roi.py
nauscopia-0.0.0.dist-info/LICENSE
nauscopia-0.0.0.dist-info/METADATA
nauscopia-0.0.0.dist-info/WHEEL
nauscopia-0.0.0.dist-info/entry_points.txt
nauscopia-0.0.0.dist-info/top_level.txt
nauscopia-0.0.0.dist-info/RECORD
