Metadata-Version: 2.1
Name: nauscopia
Version: 0.0.0
Summary: Computer vision utilities for maritime SAR purposes.
Author-email: Florian Vahl <florian@flova.de>, Petrosilius <petrosilius@posteo.de>
Maintainer-email: Andreas Motl <andreas.motl@panodata.org>
License:                     GNU AFFERO GENERAL PUBLIC LICENSE
Project-URL: changelog, https://codeberg.org/sarcam/nauscopia/src/branch/main/CHANGES.md
Project-URL: documentation, https://sarcam.flova.de/
Project-URL: homepage, https://sarcam.flova.de/
Project-URL: repository, https://codeberg.org/sarcam/nauscopia
Keywords: computer vision,cv,deep learning,object detection,real-time video processing,sar,scene parsing,search and rescue,semantic segmentation,swiss army knife,toolbox,yolo
Classifier: Development Status :: 1 - Planning
Classifier: Intended Audience :: Developers
Classifier: Intended Audience :: Education
Classifier: Intended Audience :: End Users/Desktop
Classifier: Intended Audience :: Information Technology
Classifier: Intended Audience :: Manufacturing
Classifier: Intended Audience :: Science/Research
Classifier: Intended Audience :: System Administrators
Classifier: License :: OSI Approved :: European Union Public Licence 1.2 (EUPL 1.2)
Classifier: License :: OSI Approved :: GNU Affero General Public License v3
Classifier: Programming Language :: Python :: 3 :: Only
Classifier: Programming Language :: Python :: 3.9
Classifier: Programming Language :: Python :: 3.10
Classifier: Programming Language :: Python :: 3.11
Classifier: Programming Language :: Python :: 3.12
Classifier: Programming Language :: Python :: Implementation :: CPython
Classifier: Topic :: Education
Classifier: Topic :: File Formats
Classifier: Topic :: Scientific/Engineering
Classifier: Topic :: Software Development :: Libraries :: Python Modules
Requires-Python: <3.13,>=3.9
License-File: LICENSE
Requires-Dist: attrs<25
Requires-Dist: click<9
Requires-Dist: colorlog<7
Requires-Dist: numpy<2
Requires-Dist: opencv-python<4.11
Requires-Dist: platformdirs<5
Requires-Dist: requests<3
Requires-Dist: tqdm<5
Requires-Dist: yolov10-onnx==0.3.0
Provides-Extra: all
Requires-Dist: nauscopia[develop,docs,release,test]; extra == "all"
Provides-Extra: develop
Requires-Dist: mypy<1.12; extra == "develop"
Requires-Dist: pip; extra == "develop"
Requires-Dist: poethepoet<1; extra == "develop"
Requires-Dist: pyproject-fmt<3; extra == "develop"
Requires-Dist: ruff<0.9; extra == "develop"
Requires-Dist: validate-pyproject<0.19; extra == "develop"
Provides-Extra: docs
Requires-Dist: furo; extra == "docs"
Requires-Dist: myst-parser[linkify]<5; extra == "docs"
Requires-Dist: sphinx<8.1; extra == "docs"
Requires-Dist: sphinx-autobuild==2024.10.3; extra == "docs"
Requires-Dist: sphinx-copybutton<0.6; extra == "docs"
Requires-Dist: sphinx-design-elements<0.5; extra == "docs"
Provides-Extra: release
Requires-Dist: build<2; extra == "release"
Requires-Dist: keyring; extra == "release"
Requires-Dist: twine<6; extra == "release"
Provides-Extra: test
Requires-Dist: pytest<9; extra == "test"
Requires-Dist: pytest-cov<6; extra == "test"
Requires-Dist: requests-cache<1.3; extra == "test"
